bicks/__init__.py
bicks/bicsearch.py
bicks/boundryconditionwithcTIR.py
bicks/crystalandnumber.py
bicks/eigenkpar.py
bicks/field.py
bicks/mathtool.py
bicks/photoniccrystalbandprojection.py
bicks-0.1.1.dist-info/LICENSE
bicks-0.1.1.dist-info/METADATA
bicks-0.1.1.dist-info/WHEEL
bicks-0.1.1.dist-info/top_level.txt
bicks-0.1.1.dist-info/RECORD
