Metadata-Version: 2.1
Name: bicks
Version: 0.1.1
Summary: find BICs
Home-page: https://github.com/PMRG-LE707/bicks
Author: cwxie
Author-email: cw.xie@qq.com
License: UNKNOWN
Project-URL: Bug Tracker, https://github.com/PMRG-LE707/bicks/issues
Platform: UNKNOWN
Classifier: Programming Language :: Python :: 3
Classifier: License :: OSI Approved :: MIT License
Classifier: Operating System :: OS Independent
Requires-Python: >=3.6
License-File: LICENSE
